{
  "info": {
    "_postman_id": "6ff40e9f-1593-4511-9901-634a007408b1",
    "name": "Sistema de Gestão de Despesas Parlamentares com Auditoria",
    "description": "Collection atualizada para testar os fluxos principais de criação e consulta da API NestJS com parlamentares, comissões, despesas e auditoria.",
    "schema": "https://schema.getpostman.com/json/collection/v2.1.0/collection.json",
    "_exporter_id": "39541618"
  },
  "item": [
    {
      "name": "Parlamentares",
      "item": [
        {
          "name": "Criar parlamentar",
          "event": [
            {
              "listen": "test",
              "script": {
                "type": "text/javascript",
                "exec": [
                  "const response = pm.response.json();",
                  "if (response && response.id) {",
                  "  pm.collectionVariables.set(\"parlamentarId\", String(response.id));",
                  "}"
                ]
              }
            }
          ],
          "request": {
            "method": "POST",
            "header": [
              {
                "key": "Content-Type",
                "value": "application/json"
              }
            ],
            "body": {
              "mode": "raw",
              "raw": "{\n  \"nomeCompleto\": \"João Carlos da Silva\",\n  \"nomeParlamentar\": \"João da Saúde\",\n  \"partidoAtual\": \"PT\",\n  \"numeroVotos\": 4200\n}"
            },
            "url": {
              "raw": "{{baseUrl}}/parlamentares",
              "host": [
                "{{baseUrl}}"
              ],
              "path": [
                "parlamentares"
              ]
            },
            "description": "Cria um parlamentar e salva o id retornado na variável parlamentarId."
          },
          "response": []
        },
        {
          "name": "Listar parlamentares",
          "request": {
            "method": "GET",
            "header": [],
            "url": {
              "raw": "{{baseUrl}}/parlamentares",
              "host": [
                "{{baseUrl}}"
              ],
              "path": [
                "parlamentares"
              ]
            }
          },
          "response": []
        },
        {
          "name": "Buscar parlamentar por id",
          "request": {
            "method": "GET",
            "header": [],
            "url": {
              "raw": "{{baseUrl}}/parlamentares/{{parlamentarId}}",
              "host": [
                "{{baseUrl}}"
              ],
              "path": [
                "parlamentares",
                "{{parlamentarId}}"
              ]
            }
          },
          "response": []
        },
        {
          "name": "Atualizar parlamentar",
          "request": {
            "method": "PUT",
            "header": [
              {
                "key": "Content-Type",
                "value": "application/json"
              }
            ],
            "body": {
              "mode": "raw",
              "raw": "{\n  \"numeroVotos\": 6000\n}"
            },
            "url": {
              "raw": "{{baseUrl}}/parlamentares/{{parlamentarId}}",
              "host": [
                "{{baseUrl}}"
              ],
              "path": [
                "parlamentares",
                "{{parlamentarId}}"
              ]
            },
            "description": "Atualiza parcialmente um parlamentar."
          },
          "response": []
        },
        {
          "name": "Remover parlamentar",
          "request": {
            "method": "DELETE",
            "header": [],
            "url": {
              "raw": "{{baseUrl}}/parlamentares/{{parlamentarId}}",
              "host": [
                "{{baseUrl}}"
              ],
              "path": [
                "parlamentares",
                "{{parlamentarId}}"
              ]
            }
          },
          "response": []
        }
      ]
    },
    {
      "name": "Comissões",
      "item": [
        {
          "name": "Criar comissão",
          "event": [
            {
              "listen": "test",
              "script": {
                "type": "text/javascript",
                "exec": [
                  "const response = pm.response.json();",
                  "if (response && response.id) {",
                  "  pm.collectionVariables.set(\"comissaoId\", String(response.id));",
                  "}"
                ]
              }
            }
          ],
          "request": {
            "method": "POST",
            "header": [
              {
                "key": "Content-Type",
                "value": "application/json"
              }
            ],
            "body": {
              "mode": "raw",
              "raw": "{\n  \"nome\": \"Comissão de Constituição e Justiça\",\n  \"sigla\": \"CCJ\",\n  \"tema\": \"Análise constitucional e jurídica\"\n}"
            },
            "url": {
              "raw": "{{baseUrl}}/comissoes",
              "host": [
                "{{baseUrl}}"
              ],
              "path": [
                "comissoes"
              ]
            },
            "description": "Cria uma comissão e salva o id retornado na variável comissaoId."
          },
          "response": []
        },
        {
          "name": "Listar comissões",
          "request": {
            "method": "GET",
            "header": [],
            "url": {
              "raw": "{{baseUrl}}/comissoes",
              "host": [
                "{{baseUrl}}"
              ],
              "path": [
                "comissoes"
              ]
            }
          },
          "response": []
        },
        {
          "name": "Buscar comissão por id",
          "request": {
            "method": "GET",
            "header": [],
            "url": {
              "raw": "{{baseUrl}}/comissoes/{{comissaoId}}",
              "host": [
                "{{baseUrl}}"
              ],
              "path": [
                "comissoes",
                "{{comissaoId}}"
              ]
            }
          },
          "response": []
        },
        {
          "name": "Atualizar comissão",
          "request": {
            "method": "PUT",
            "header": [
              {
                "key": "Content-Type",
                "value": "application/json"
              }
            ],
            "body": {
              "mode": "raw",
              "raw": "{\n  \"tema\": \"Análise constitucional, jurídica e regimental\"\n}"
            },
            "url": {
              "raw": "{{baseUrl}}/comissoes/{{comissaoId}}",
              "host": [
                "{{baseUrl}}"
              ],
              "path": [
                "comissoes",
                "{{comissaoId}}"
              ]
            }
          },
          "response": []
        },
        {
          "name": "Remover comissão",
          "request": {
            "method": "DELETE",
            "header": [],
            "url": {
              "raw": "{{baseUrl}}/comissoes/{{comissaoId}}",
              "host": [
                "{{baseUrl}}"
              ],
              "path": [
                "comissoes",
                "{{comissaoId}}"
              ]
            }
          },
          "response": []
        }
      ]
    },
    {
      "name": "Despesas",
      "item": [
        {
          "name": "Criar despesa",
          "event": [
            {
              "listen": "test",
              "script": {
                "type": "text/javascript",
                "exec": [
                  "const response = pm.response.json();",
                  "if (response && response.id) {",
                  "  pm.collectionVariables.set(\"despesaId\", String(response.id));",
                  "}"
                ]
              }
            }
          ],
          "request": {
            "method": "POST",
            "header": [
              {
                "key": "Content-Type",
                "value": "application/json"
              }
            ],
            "body": {
              "mode": "raw",
              "raw": "{\n  \"descricao\": \"Abastecimento do veículo oficial\",\n  \"valor\": 1800,\n  \"categoria\": \"COMBUSTIVEL\",\n  \"data\": \"2026-04-25\",\n  \"parlamentarId\": {{parlamentarId}}\n}"
            },
            "url": {
              "raw": "{{baseUrl}}/despesas",
              "host": [
                "{{baseUrl}}"
              ],
              "path": [
                "despesas"
              ]
            },
            "description": "Cria uma despesa ligada ao parlamentar criado e salva o id retornado na variável despesaId."
          },
          "response": []
        },
        {
          "name": "Listar despesas",
          "request": {
            "method": "GET",
            "header": [],
            "url": {
              "raw": "{{baseUrl}}/despesas",
              "host": [
                "{{baseUrl}}"
              ],
              "path": [
                "despesas"
              ]
            }
          },
          "response": []
        },
        {
          "name": "Buscar despesa por id",
          "request": {
            "method": "GET",
            "header": [],
            "url": {
              "raw": "{{baseUrl}}/despesas/{{despesaId}}",
              "host": [
                "{{baseUrl}}"
              ],
              "path": [
                "despesas",
                "{{despesaId}}"
              ]
            }
          },
          "response": []
        },
        {
          "name": "Buscar despesas por categoria",
          "request": {
            "method": "GET",
            "header": [],
            "url": {
              "raw": "{{baseUrl}}/despesas/categoria/{{categoria}}",
              "host": [
                "{{baseUrl}}"
              ],
              "path": [
                "despesas",
                "categoria",
                "{{categoria}}"
              ]
            }
          },
          "response": []
        },
        {
          "name": "Atualizar despesa",
          "request": {
            "method": "PUT",
            "header": [
              {
                "key": "Content-Type",
                "value": "application/json"
              }
            ],
            "body": {
              "mode": "raw",
              "raw": "{\n  \"descricao\": \"Divulgação institucional nas redes\",\n  \"valor\": 9000,\n  \"categoria\": \"DIVULGACAO\",\n  \"data\": \"2026-04-26\",\n  \"parlamentarId\": {{parlamentarId}}\n}"
            },
            "url": {
              "raw": "{{baseUrl}}/despesas/{{despesaId}}",
              "host": [
                "{{baseUrl}}"
              ],
              "path": [
                "despesas",
                "{{despesaId}}"
              ]
            },
            "description": "Atualiza parcialmente a despesa existente."
          },
          "response": []
        },
        {
          "name": "Remover despesa",
          "request": {
            "method": "DELETE",
            "header": [],
            "url": {
              "raw": "{{baseUrl}}/despesas/{{despesaId}}",
              "host": [
                "{{baseUrl}}"
              ],
              "path": [
                "despesas",
                "{{despesaId}}"
              ]
            }
          },
          "response": []
        }
      ]
    },
    {
      "name": "Auditoria",
      "item": [
        {
          "name": "Listar logs de auditoria",
          "request": {
            "method": "GET",
            "header": [],
            "url": {
              "raw": "{{baseUrl}}/audit/logs",
              "host": [
                "{{baseUrl}}"
              ],
              "path": [
                "audit",
                "logs"
              ]
            },
            "description": "Consulta os logs de auditoria gerados automaticamente após criações na base principal."
          },
          "response": []
        }
      ]
    },
    {
      "name": "Testes de erro",
      "item": [
        {
          "name": "Erro 404 - parlamentar inexistente",
          "request": {
            "method": "GET",
            "header": [],
            "url": {
              "raw": "{{baseUrl}}/parlamentares/999",
              "host": [
                "{{baseUrl}}"
              ],
              "path": [
                "parlamentares",
                "999"
              ]
            }
          },
          "response": []
        },
        {
          "name": "Erro 404 - comissão inexistente",
          "request": {
            "method": "GET",
            "header": [],
            "url": {
              "raw": "{{baseUrl}}/comissoes/999",
              "host": [
                "{{baseUrl}}"
              ],
              "path": [
                "comissoes",
                "999"
              ]
            }
          },
          "response": []
        },
        {
          "name": "Erro 404 - despesa inexistente",
          "request": {
            "method": "GET",
            "header": [],
            "url": {
              "raw": "{{baseUrl}}/despesas/999",
              "host": [
                "{{baseUrl}}"
              ],
              "path": [
                "despesas",
                "999"
              ]
            }
          },
          "response": []
        },
        {
          "name": "Erro 400 - despesa inválida",
          "request": {
            "method": "POST",
            "header": [
              {
                "key": "Content-Type",
                "value": "application/json"
              }
            ],
            "body": {
              "mode": "raw",
              "raw": "{\n  \"descricao\": \"\",\n  \"valor\": -10,\n  \"categoria\": \"TESTE\",\n  \"data\": \"abc\",\n  \"parlamentarId\": 0\n}"
            },
            "url": {
              "raw": "{{baseUrl}}/despesas",
              "host": [
                "{{baseUrl}}"
              ],
              "path": [
                "despesas"
              ]
            }
          },
          "response": []
        }
      ]
    }
  ],
  "variable": [
    {
      "key": "baseUrl",
      "value": "http://localhost:3000"
    },
    {
      "key": "parlamentarId",
      "value": "1"
    },
    {
      "key": "comissaoId",
      "value": "1"
    },
    {
      "key": "despesaId",
      "value": "1"
    },
    {
      "key": "partido",
      "value": "PSB"
    },
    {
      "key": "categoria",
      "value": "COMBUSTIVEL"
    }
  ]
}